{
"1K45R": "char16_t",
"A*PBLZ": "alignas",
"AOFPBL": "alignof",
"APLZ": "asm",
"K345R": "char32_t",
"K45R8": "char8_t",
"KAELD": "co_yield",
"KOFRPL": "compl",
"KOPBTS": "const",
"KP*EPT": "noexcept",
"KPO*ER": "xor_eq",
"KPO*R": "xor",
"KPREFRPL": "reflexpr",
"KPURPB": "extern",
"KRURPB": "co_return",
"KW*PBT": "not_eq",
"KWAEUT": "co_await",
"KWHART": "wchar_t",
"KWOR": "or_eq",
"PHAOUBLT": "mutable",
"PRA*S": "reinterpret_cast",
"PWOEURT": "bitor",
"SAO*EUPBD": "unsigned",
"SAOEUFZ": "sizeof",
"SKP*E": "and_eq",
"SKWEUT": "bitand",
"SPHAPLS": "asm",
"SRAOEUFD": "synchronized",
"ST*BGTS": "static_cast",
"STARBGTS": "static_assert",
"STKPH": "const",
"STKPH*S": "const_cast",
"STKPH-L": "consteval",
"STKPH-P": "constexpr",
"STKPH-PB": "constinit",
"STPHAEUPL": "namespace",
"TAOEUBL": "typename",
"TAOEUFPD": "typedef",
"TAOPD": "typeid",
"THRELD": "thread_local",
"TK*BGS": "dynamic_cast",
"TKAOEUP": "decltype",
"TKPHEUBGT": "atomic_commit",
"TKPHEUBLG": "atomic_cancel",
"TKPW*T": "goto",
"TPHEUPBGT": "atomic_noexcept",
"TPHURPLT": "nullptr",
"TPRAO*EPB": "inline"
}
